README.md
example.py
setup.py
linptech/__init__.py
linptech/constant.py
linptech/crc8.py
linptech/linptech_protocol.py
linptech/packet.py
linptech/serial_communicator.py
linptech/test.py
linptech.egg-info/PKG-INFO
linptech.egg-info/SOURCES.txt
linptech.egg-info/dependency_links.txt
linptech.egg-info/requires.txt
linptech.egg-info/top_level.txt