Metadata-Version: 1.0
Name: linptech
Version: 0.2.4
Summary: Linptech serial protocol
Home-page: https://github.com/yangguozhanzhao/linptech
Author: yangzhan
Author-email: 728074993@qq.com
License: UNKNOWN
Platform: UNKNOWN
